__init__.py
geom_props/__init__.py
geom_props/geom_props.py
geom_props-1.0.0.dist-info/METADATA
geom_props-1.0.0.dist-info/WHEEL
geom_props-1.0.0.dist-info/top_level.txt
geom_props-1.0.0.dist-info/RECORD
