Metadata-Version: 2.1
Name: geom-props
Version: 1.0.0
Requires-Python: >=3.7
Requires-Dist: shapely (<2.1,>=2)
Requires-Dist: pyproj (<3.5,>=3.4)
